sesame/__init__.py
sesame/backends.py
sesame/decorators.py
sesame/middleware.py
sesame/packers.py
sesame/settings.py
sesame/tokens.py
sesame/tokens_v1.py
sesame/tokens_v2.py
sesame/utils.py
sesame/views.py
django_sesame-3.2.1.dist-info/LICENSE
django_sesame-3.2.1.dist-info/METADATA
django_sesame-3.2.1.dist-info/WHEEL
django_sesame-3.2.1.dist-info/RECORD
